PKiL/Utils.py
PKiL/__init__.py
PKiL/process.py
cpkil-0.2.3.dist-info/METADATA
cpkil-0.2.3.dist-info/WHEEL
cpkil-0.2.3.dist-info/top_level.txt
cpkil-0.2.3.dist-info/RECORD
