Metadata-Version: 2.1
Name: cpkil
Version: 0.2.3
Summary: CPR Python Package
Home-page: UNKNOWN
Author: Jinendra Malekar
Author-email: <jmalekar@email.sc.edu>
License: UNKNOWN
Platform: UNKNOWN
Classifier: Development Status :: 1 - Planning
Classifier: Intended Audience :: Developers
Classifier: Programming Language :: Python :: 3
Classifier: Operating System :: Unix
Classifier: Operating System :: MacOS :: MacOS X
Classifier: Operating System :: Microsoft :: Windows
Requires-Dist: certifi
Requires-Dist: charset-normalizer
Requires-Dist: click
Requires-Dist: filelock
Requires-Dist: Flask
Requires-Dist: Flask-Cors
Requires-Dist: gensim
Requires-Dist: huggingface-hub
Requires-Dist: idna
Requires-Dist: itsdangerous
Requires-Dist: Jinja2
Requires-Dist: joblib
Requires-Dist: MarkupSafe
Requires-Dist: nltk
Requires-Dist: numpy
Requires-Dist: packaging
Requires-Dist: Pillow
Requires-Dist: pyparsing
Requires-Dist: PyYAML
Requires-Dist: regex
Requires-Dist: requests
Requires-Dist: scikit-learn
Requires-Dist: scipy
Requires-Dist: sentence-transformers
Requires-Dist: sentencepiece
Requires-Dist: six
Requires-Dist: smart-open
Requires-Dist: threadpoolctl
Requires-Dist: tokenizers
Requires-Dist: torch
Requires-Dist: torchvision
Requires-Dist: tqdm
Requires-Dist: transformers
Requires-Dist: typing-extensions
Requires-Dist: urllib3
Requires-Dist: Werkzeug
